zipcommon/__init__.py
zipcommon-0.0.1.dist-info/LICENCE.txt
zipcommon-0.0.1.dist-info/METADATA
zipcommon-0.0.1.dist-info/WHEEL
zipcommon-0.0.1.dist-info/top_level.txt
zipcommon-0.0.1.dist-info/RECORD
